LICENSE
MANIFEST.in
README.md
setup.cfg
setup.py
gh/__about__.py
gh/__init__.py
gh/gh.py
gh_api.egg-info/PKG-INFO
gh_api.egg-info/SOURCES.txt
gh_api.egg-info/dependency_links.txt
gh_api.egg-info/entry_points.txt
gh_api.egg-info/not-zip-safe
gh_api.egg-info/requires.txt
gh_api.egg-info/top_level.txt