Metadata-Version: 2.1
Name: gh-api
Version: 0.0.1
Summary: Low-level GitHub API request interface. With caching
Home-page: https://github.com/dvershinin/gh
Author: Danila Vershinin
Author-email: info@getpagespeed.com
License: BSD
Platform: UNKNOWN
Classifier: Intended Audience :: Developers
Classifier: Intended Audience :: System Administrators
Classifier: Operating System :: OS Independent
Classifier: Topic :: Software Development
Provides-Extra: tests
